nessie/recorder/__init__.py
nessie_recorder-1.0.6.dist-info/LICENSE
nessie_recorder-1.0.6.dist-info/METADATA
nessie_recorder-1.0.6.dist-info/WHEEL
nessie_recorder-1.0.6.dist-info/entry_points.txt
nessie_recorder-1.0.6.dist-info/top_level.txt
nessie_recorder-1.0.6.dist-info/RECORD
