Metadata-Version: 2.1
Name: nessie-recorder
Version: 1.0.6
Summary: Tools for Nessie Circuit energy harvesting recorder
Author: Kai Geissdoerfer
License: MIT
Platform: UNKNOWN
License-File: LICENSE
Requires-Dist: numpy
Requires-Dist: scipy
Requires-Dist: click
Requires-Dist: h5py
Requires-Dist: pandas
Requires-Dist: crccheck
Requires-Dist: matplotlib
